manydo/__init__.py
manydo/map.py
manydo/no_context.py
manydo/parallel_tqdm.py
manydo-0.1.6.dist-info/LICENSE
manydo-0.1.6.dist-info/WHEEL
manydo-0.1.6.dist-info/METADATA
manydo-0.1.6.dist-info/RECORD
