Metadata-Version: 2.1
Name: manydo
Version: 0.1.6
Summary: Dead-simple parallel execution.
Home-page: https://github.com/malyvsen/manydo
License: MIT
Keywords: parallelism,multithreading
Author: malyvsen
Requires-Python: >=3.6,<4.0
Classifier: License :: OSI Approved :: MIT License
Classifier: Programming Language :: Python :: 3
Classifier: Programming Language :: Python :: 3.6
Classifier: Programming Language :: Python :: 3.7
Classifier: Programming Language :: Python :: 3.8
Classifier: Programming Language :: Python :: 3.9
Requires-Dist: joblib (>=1.0.0,<2.0.0)
Requires-Dist: tqdm (>=4,<5)
Project-URL: Repository, https://github.com/malyvsen/manydo
